CawBusPython/CAN.py
CawBusPython/Protocol.py
CawBusPython/Transmit.py
CawBusPython/__init__.py
CawBus-1.0.0.dist-info/LICENSE
CawBus-1.0.0.dist-info/METADATA
CawBus-1.0.0.dist-info/WHEEL
CawBus-1.0.0.dist-info/top_level.txt
CawBus-1.0.0.dist-info/RECORD
